NettyShizhanJingsui/README.md
NettyShizhanJingsui/__init__.py
NettyShizhanJingsui/__main__.py
NettyShizhanJingsui/file.epub
NettyShizhanJingsui/index.html
NettyShizhanJingsui/css/__init__.py
NettyShizhanJingsui/css/annotations.css
NettyShizhanJingsui/css/main.css
NettyShizhanJingsui/css/normalize.css
NettyShizhanJingsui/css/popup.css
NettyShizhanJingsui/font/__init__.py
NettyShizhanJingsui/font/fontello.eot
NettyShizhanJingsui/font/fontello.svg
NettyShizhanJingsui/font/fontello.ttf
NettyShizhanJingsui/font/fontello.woff
NettyShizhanJingsui/img/__init__.py
NettyShizhanJingsui/img/annotator-glyph-sprite.png
NettyShizhanJingsui/img/annotator-icon-sprite.png
NettyShizhanJingsui/img/apple-touch-icon.png
NettyShizhanJingsui/img/cancelfullscreen.png
NettyShizhanJingsui/img/close.png
NettyShizhanJingsui/img/fullscreen.png
NettyShizhanJingsui/img/loader.gif
NettyShizhanJingsui/img/menu-icon.png
NettyShizhanJingsui/img/save.png
NettyShizhanJingsui/img/saved.png
NettyShizhanJingsui/img/settings-s.png
NettyShizhanJingsui/img/settings.png
NettyShizhanJingsui/img/star.png
NettyShizhanJingsui/js/__init__.py
NettyShizhanJingsui/js/epub.js
NettyShizhanJingsui/js/epub.min.js
NettyShizhanJingsui/js/epub.min.map
NettyShizhanJingsui/js/hooks.min.js
NettyShizhanJingsui/js/hooks.min.map
NettyShizhanJingsui/js/reader.js
NettyShizhanJingsui/js/reader.js.map
NettyShizhanJingsui/js/reader.min.js
NettyShizhanJingsui/js/reader.min.map
NettyShizhanJingsui/js/hooks/__init__.py
NettyShizhanJingsui/js/hooks/extensions/__init__.py
NettyShizhanJingsui/js/hooks/extensions/highlight.js
NettyShizhanJingsui/js/libs/__init__.py
NettyShizhanJingsui/js/libs/jquery.min.js
NettyShizhanJingsui/js/libs/localforage.min.js
NettyShizhanJingsui/js/libs/screenfull.js
NettyShizhanJingsui/js/libs/screenfull.min.js
NettyShizhanJingsui/js/libs/zip.min.js
NettyShizhanJingsui/js/plugins/__init__.py
NettyShizhanJingsui/js/plugins/hypothesis.js
NettyShizhanJingsui/js/plugins/search.js
netty_shizhan_jingsui-2024.3.1.0.dist-info/METADATA
netty_shizhan_jingsui-2024.3.1.0.dist-info/WHEEL
netty_shizhan_jingsui-2024.3.1.0.dist-info/entry_points.txt
netty_shizhan_jingsui-2024.3.1.0.dist-info/top_level.txt
netty_shizhan_jingsui-2024.3.1.0.dist-info/RECORD
